[
    {
        "id": 1,
        "title": "Введение в JavaScript",
        "date": "2026-03-01",
        "description": "Основные концепции языка для начинающих: переменные, типы данных, функции и многое другое.",
        "file": "posts/1.md"
    },
    {
        "id": 2,
        "title": "Работа с DOM и событиями",
        "date": "2026-03-05",
        "description": "Как взаимодействовать с веб-страницей, изменять элементы и обрабатывать действия пользователя.",
        "file": "posts/2.md"
    },
    {
        "id": 3,
        "title": "Асинхронный JavaScript: Promise и async/await",
        "date": "2026-03-10",
        "description": "Узнайте, как работать с асинхронным кодом, загружать данные и обрабатывать ошибки.",
        "file": "posts/3.md"
    }
]